{
 "prod_path": "spark/src/main/java/com/nflabs/zeppelin/spark/SparkInterpreter.java",
 "prod_sha1": "acd79a0bd9310e0ea12c0bcb63c9f0652772f499",
 "repository": "zeppelin",
 "test_path": "spark/src/test/java/com/nflabs/zeppelin/spark/SparkInterpreterTest.java",
 "test_sha1": "acd79a0bd9310e0ea12c0bcb63c9f0652772f499",
 "commit_between": 0,
 "prod_qual": "com/nflabs/zeppelin/spark/SparkInterpreter.java",
 "prod_time": {
  "$date": 1418032200000
 },
 "prod_typ": "EDIT",
 "sample_type": "POSITIVE",
 "test_qual": "com/nflabs/zeppelin/spark/SparkInterpreterTest.java",
 "test_time": {
  "$date": 1418032200000
 },
 "test_typ": "EDIT",
 "add_annotation_line": 0,
 "add_call_line": 0,
 "add_classname_line": 0,
 "add_condition_line": 0,
 "add_field_line": 0,
 "add_import_line": 0,
 "add_packageid_line": 0,
 "add_parameter_line": 0,
 "add_return_line": 0,
 "del_annotation_line": 0,
 "del_call_line": 5,
 "del_classname_line": 0,
 "del_condition_line": 2,
 "del_field_line": 0,
 "del_import_line": 0,
 "del_packageid_line": 0,
 "del_parameter_line": 2,
 "del_return_line": 0
}