{
 "prod_path": "python/src/main/java/org/apache/zeppelin/python/PythonInterpreter.java",
 "prod_sha1": "c806d4a4c7c2e49001928866a91ebb501e3608c8",
 "repository": "zeppelin",
 "prod_qual": "org/apache/zeppelin/python/PythonInterpreter.java",
 "prod_time": {
  "$date": 1466092206000
 },
 "prod_typ": "EDIT",
 "sample_type": "NEGATIVE",
 "test_path": "python/src/test/java/org/apache/zeppelin/python/PythonInterpreterTest.java",
 "test_qual": "org/apache/zeppelin/python/PythonInterpreterTest.java",
 "add_annotation_line": 0,
 "add_call_line": 3,
 "add_classname_line": 0,
 "add_condition_line": 2,
 "add_field_line": 1,
 "add_import_line": 0,
 "add_packageid_line": 0,
 "add_parameter_line": 0,
 "add_return_line": 1,
 "del_annotation_line": 1,
 "del_call_line": 5,
 "del_classname_line": 0,
 "del_condition_line": 3,
 "del_field_line": 1,
 "del_import_line": 0,
 "del_packageid_line": 0,
 "del_parameter_line": 4,
 "del_return_line": 0,
 "test_typ": "Non"
}