{
 "prod_path": "markdown/src/main/java/com/nflabs/zeppelin/markdown/Markdown.java",
 "prod_sha1": "4954618a253f68e85795bc4a124596ec936d62a8",
 "repository": "zeppelin",
 "prod_qual": "com/nflabs/zeppelin/markdown/Markdown.java",
 "prod_time": {
  "$date": 1409889029000
 },
 "prod_typ": "EDIT",
 "sample_type": "NEGATIVE",
 "test_path": "markdown/src/test/java/com/nflabs/zeppelin/markdown/MarkdownTest.java",
 "test_qual": "com/nflabs/zeppelin/markdown/MarkdownTest.java",
 "add_annotation_line": 0,
 "add_call_line": 0,
 "add_classname_line": 0,
 "add_condition_line": 0,
 "add_field_line": 0,
 "add_import_line": 0,
 "add_packageid_line": 0,
 "add_parameter_line": 0,
 "add_return_line": 1,
 "del_annotation_line": 0,
 "del_call_line": 0,
 "del_classname_line": 0,
 "del_condition_line": 0,
 "del_field_line": 0,
 "del_import_line": 0,
 "del_packageid_line": 0,
 "del_parameter_line": 0,
 "del_return_line": 1,
 "test_typ": "Non"
}