{
 "prod_path": "engine/schema/src/com/cloud/upgrade/dao/DatabaseAccessObject.java",
 "prod_sha1": "e26855e2849960951fd27fcb394c19a5b4bb2755",
 "repository": "cloudstack",
 "test_path": "engine/schema/test/com/cloud/upgrade/dao/DatabaseAccessObjectTest.java",
 "test_sha1": "e26855e2849960951fd27fcb394c19a5b4bb2755",
 "commit_between": 0,
 "prod_qual": "com/cloud/upgrade/dao/DatabaseAccessObject.java",
 "prod_time": {
  "$date": 1406849793000
 },
 "prod_typ": "EDIT",
 "sample_type": "POSITIVE",
 "test_qual": "com/cloud/upgrade/dao/DatabaseAccessObjectTest.java",
 "test_time": {
  "$date": 1406849793000
 },
 "test_typ": "EDIT",
 "add_annotation_line": 0,
 "add_call_line": 3,
 "add_classname_line": 0,
 "add_condition_line": 0,
 "add_field_line": 0,
 "add_import_line": 0,
 "add_packageid_line": 0,
 "add_parameter_line": 0,
 "add_return_line": 0,
 "del_annotation_line": 0,
 "del_call_line": 3,
 "del_classname_line": 0,
 "del_condition_line": 0,
 "del_field_line": 0,
 "del_import_line": 0,
 "del_packageid_line": 0,
 "del_parameter_line": 0,
 "del_return_line": 0
}