{
 "prod_path": "thirdparty/apache-log4j-1.2.16/src/main/java/org/apache/log4j/LogManager.java",
 "prod_sha1": "22d5eac400cdc951bfbcebdcb237464aa3de00fb",
 "repository": "cloudstack",
 "test_path": "thirdparty/apache-log4j-1.2.16/tests/src/java/org/apache/log4j/LogManagerTest.java",
 "test_sha1": "22d5eac400cdc951bfbcebdcb237464aa3de00fb",
 "commit_between": 0,
 "prod_qual": "org/apache/log4j/LogManager.java",
 "prod_time": {
  "$date": 1308676521000
 },
 "prod_typ": "CREATE",
 "sample_type": "POSITIVE",
 "test_qual": "org/apache/log4j/LogManagerTest.java",
 "test_time": {
  "$date": 1308676521000
 },
 "test_typ": "CREATE",
 "add_annotation_line": 0,
 "add_call_line": 34,
 "add_classname_line": 1,
 "add_condition_line": 8,
 "add_field_line": 8,
 "add_import_line": 14,
 "add_packageid_line": 1,
 "add_parameter_line": 11,
 "add_return_line": 8,
 "del_annotation_line": 0,
 "del_call_line": 0,
 "del_classname_line": 0,
 "del_condition_line": 0,
 "del_field_line": 0,
 "del_import_line": 0,
 "del_packageid_line": 0,
 "del_parameter_line": 0,
 "del_return_line": 0
}