{
 "prod_path": "JodaTime/src/java/org/joda/time/field/BaseDateTimeField.java",
 "prod_sha1": "272609b3d34d56a6c6fd3b1b8eaed3bb87682632",
 "repository": "joda-time",
 "prod_qual": "org/joda/time/field/BaseDateTimeField.java",
 "prod_time": {
  "$date": 1106782346000
 },
 "prod_typ": "EDIT",
 "sample_type": "NEGATIVE",
 "test_path": "JodaTime/src/test/org/joda/time/field/TestBaseDateTimeField.java",
 "test_qual": "org/joda/time/field/TestBaseDateTimeField.java",
 "add_annotation_line": 0,
 "add_call_line": 17,
 "add_classname_line": 0,
 "add_condition_line": 11,
 "add_field_line": 0,
 "add_import_line": 0,
 "add_packageid_line": 0,
 "add_parameter_line": 1,
 "add_return_line": 2,
 "del_annotation_line": 0,
 "del_call_line": 4,
 "del_classname_line": 0,
 "del_condition_line": 0,
 "del_field_line": 0,
 "del_import_line": 0,
 "del_packageid_line": 0,
 "del_parameter_line": 0,
 "del_return_line": 0,
 "test_typ": "Non"
}