{
 "prod_path": "storm-core/src/jvm/org/apache/storm/security/auth/SaslTransportPlugin.java",
 "prod_sha1": "3da11a2723213f0b1788c9b5766226124c1f4297",
 "repository": "storm",
 "prod_qual": "jvm/org/apache/storm/security/auth/SaslTransportPlugin.java",
 "prod_time": {
  "$date": 1482354492000
 },
 "prod_typ": "EDIT",
 "sample_type": "NEGATIVE",
 "test_path": "storm-core/test/jvm/org/apache/storm/security/auth/SaslTransportPluginTest.java",
 "test_qual": "jvm/org/apache/storm/security/auth/SaslTransportPluginTest.java",
 "add_annotation_line": 0,
 "add_call_line": 1,
 "add_classname_line": 0,
 "add_condition_line": 1,
 "add_field_line": 0,
 "add_import_line": 0,
 "add_packageid_line": 0,
 "add_parameter_line": 0,
 "add_return_line": 0,
 "del_annotation_line": 0,
 "del_call_line": 1,
 "del_classname_line": 0,
 "del_condition_line": 0,
 "del_field_line": 1,
 "del_import_line": 0,
 "del_packageid_line": 0,
 "del_parameter_line": 1,
 "del_return_line": 0,
 "test_typ": "Non"
}