{
 "prod_path": "activemq-core/src/main/java/org/apache/activemq/transport/udp/UdpTransport.java",
 "prod_sha1": "4f446eb0254d720b318d9c2de1ee712307a85842",
 "repository": "activemq",
 "test_path": "activemq-core/src/test/java/org/apache/activemq/transport/udp/UdpTransportTest.java",
 "test_sha1": "4f446eb0254d720b318d9c2de1ee712307a85842",
 "commit_between": 0,
 "prod_qual": "org/apache/activemq/transport/udp/UdpTransport.java",
 "prod_time": {
  "$date": 1141927592000
 },
 "prod_typ": "EDIT",
 "sample_type": "POSITIVE",
 "test_qual": "org/apache/activemq/transport/udp/UdpTransportTest.java",
 "test_time": {
  "$date": 1141927592000
 },
 "test_typ": "EDIT",
 "add_annotation_line": 0,
 "add_call_line": 7,
 "add_classname_line": 0,
 "add_condition_line": 5,
 "add_field_line": 8,
 "add_import_line": 0,
 "add_packageid_line": 0,
 "add_parameter_line": 9,
 "add_return_line": 4,
 "del_annotation_line": 0,
 "del_call_line": 1,
 "del_classname_line": 0,
 "del_condition_line": 0,
 "del_field_line": 2,
 "del_import_line": 0,
 "del_packageid_line": 0,
 "del_parameter_line": 2,
 "del_return_line": 2
}