{
 "prod_path": "izpack-core/src/main/java/com/izforge/izpack/merge/resolve/PathResolver.java",
 "prod_sha1": "5d1ab894d5b0959ac9aed5b728b24754fa462da3",
 "repository": "izpack",
 "test_path": "izpack-core/src/test/java/com/izforge/izpack/merge/resolve/PathResolverTest.java",
 "test_sha1": "5d1ab894d5b0959ac9aed5b728b24754fa462da3",
 "commit_between": 0,
 "prod_qual": "com/izforge/izpack/merge/resolve/PathResolver.java",
 "prod_time": {
  "$date": 1266440969000
 },
 "prod_typ": "EDIT",
 "sample_type": "POSITIVE",
 "test_qual": "com/izforge/izpack/merge/resolve/PathResolverTest.java",
 "test_time": {
  "$date": 1266440969000
 },
 "test_typ": "EDIT",
 "add_annotation_line": 0,
 "add_call_line": 7,
 "add_classname_line": 0,
 "add_condition_line": 2,
 "add_field_line": 0,
 "add_import_line": 1,
 "add_packageid_line": 0,
 "add_parameter_line": 0,
 "add_return_line": 3,
 "del_annotation_line": 0,
 "del_call_line": 2,
 "del_classname_line": 0,
 "del_condition_line": 0,
 "del_field_line": 0,
 "del_import_line": 0,
 "del_packageid_line": 0,
 "del_parameter_line": 1,
 "del_return_line": 1
}