{
 "prod_path": "izpack-core/src/main/java/com/izforge/izpack/merge/panel/PanelMerge.java",
 "prod_sha1": "4af79b7b417cd6c0ca3f124fb1a1556ead178e29",
 "repository": "izpack",
 "test_path": "izpack-test/src/test/java/com/izforge/izpack/merge/panel/PanelMergeTest.java",
 "test_sha1": "4af79b7b417cd6c0ca3f124fb1a1556ead178e29",
 "commit_between": 0,
 "prod_qual": "com/izforge/izpack/merge/panel/PanelMerge.java",
 "prod_time": {
  "$date": 1266908802000
 },
 "prod_typ": "EDIT",
 "sample_type": "POSITIVE",
 "test_qual": "com/izforge/izpack/merge/panel/PanelMergeTest.java",
 "test_time": {
  "$date": 1266908802000
 },
 "test_typ": "EDIT",
 "add_annotation_line": 0,
 "add_call_line": 1,
 "add_classname_line": 0,
 "add_condition_line": 5,
 "add_field_line": 1,
 "add_import_line": 0,
 "add_packageid_line": 0,
 "add_parameter_line": 1,
 "add_return_line": 0,
 "del_annotation_line": 0,
 "del_call_line": 3,
 "del_classname_line": 0,
 "del_condition_line": 4,
 "del_field_line": 2,
 "del_import_line": 1,
 "del_packageid_line": 0,
 "del_parameter_line": 1,
 "del_return_line": 1
}