{
 "prod_path": "src/java/org/apache/commons/math/linear/RealMatrixImpl.java",
 "prod_sha1": "483f55064e9953267fa1fdc8819aac9a3c239a30",
 "repository": "commons-math",
 "test_path": "src/test/org/apache/commons/math/linear/RealMatrixImplTest.java",
 "test_sha1": "483f55064e9953267fa1fdc8819aac9a3c239a30",
 "commit_between": 0,
 "prod_qual": "org/apache/commons/math/linear/RealMatrixImpl.java",
 "prod_time": {
  "$date": 1228485950000
 },
 "prod_typ": "EDIT",
 "sample_type": "POSITIVE",
 "test_qual": "org/apache/commons/math/linear/RealMatrixImplTest.java",
 "test_time": {
  "$date": 1228485950000
 },
 "test_typ": "EDIT",
 "add_annotation_line": 0,
 "add_call_line": 5,
 "add_classname_line": 0,
 "add_condition_line": 6,
 "add_field_line": 2,
 "add_import_line": 0,
 "add_packageid_line": 0,
 "add_parameter_line": 0,
 "add_return_line": 5,
 "del_annotation_line": 1,
 "del_call_line": 3,
 "del_classname_line": 0,
 "del_condition_line": 3,
 "del_field_line": 2,
 "del_import_line": 0,
 "del_packageid_line": 0,
 "del_parameter_line": 5,
 "del_return_line": 3
}