{
 "prod_path": "src/org/jruby/util/ShellLauncher.java",
 "prod_sha1": "5bead3fbb7fd944d836ad84daf20904385889af9",
 "repository": "jruby",
 "prod_qual": "org/jruby/util/ShellLauncher.java",
 "prod_time": {
  "$date": 1222636779000
 },
 "prod_typ": "EDIT",
 "sample_type": "NEGATIVE",
 "test_path": "test/org/jruby/util/ShellLauncherTest.java",
 "test_qual": "org/jruby/util/ShellLauncherTest.java",
 "add_annotation_line": 0,
 "add_call_line": 0,
 "add_classname_line": 0,
 "add_condition_line": 0,
 "add_field_line": 0,
 "add_import_line": 0,
 "add_packageid_line": 0,
 "add_parameter_line": 0,
 "add_return_line": 0,
 "del_annotation_line": 0,
 "del_call_line": 0,
 "del_classname_line": 0,
 "del_condition_line": 0,
 "del_field_line": 0,
 "del_import_line": 0,
 "del_packageid_line": 0,
 "del_parameter_line": 0,
 "del_return_line": 1,
 "test_typ": "Non"
}