{
 "prod_path": "src/main/java/org/jsoup/parser/HtmlTreeBuilder.java",
 "prod_sha1": "7ff7c43e9fbf4bbaf2b4517b3d4f8a429d87d3bb",
 "repository": "jsoup",
 "prod_qual": "org/jsoup/parser/HtmlTreeBuilder.java",
 "prod_time": {
  "$date": 1545537409000
 },
 "prod_typ": "EDIT",
 "sample_type": "NEGATIVE",
 "test_path": "src/test/java/org/jsoup/parser/HtmlTreeBuilderTest.java",
 "test_qual": "org/jsoup/parser/HtmlTreeBuilderTest.java",
 "add_annotation_line": 0,
 "add_call_line": 14,
 "add_classname_line": 0,
 "add_condition_line": 8,
 "add_field_line": 0,
 "add_import_line": 0,
 "add_packageid_line": 0,
 "add_parameter_line": 0,
 "add_return_line": 1,
 "del_annotation_line": 0,
 "del_call_line": 14,
 "del_classname_line": 0,
 "del_condition_line": 8,
 "del_field_line": 0,
 "del_import_line": 0,
 "del_packageid_line": 0,
 "del_parameter_line": 0,
 "del_return_line": 1,
 "test_typ": "Non"
}